absdata/__init__.py
absdata-0.3.1.dist-info/LICENSE.txt
absdata-0.3.1.dist-info/METADATA
absdata-0.3.1.dist-info/WHEEL
absdata-0.3.1.dist-info/top_level.txt
absdata-0.3.1.dist-info/RECORD
