Metadata-Version: 2.1
Name: absdata
Version: 0.3.1
Summary: Access to ABS data and correspondencies
Home-page: https://github.com/varunsatish/ABS_Package
Author: Varun Satish
Author-email: varun.satish96@gmail.com
License: MIT
Platform: UNKNOWN
Requires-Dist: pandas
Requires-Dist: sqlalchemy
